td0update/__init__.py
td0update/core.py
td0update_darshan-0.1.0.dist-info/METADATA
td0update_darshan-0.1.0.dist-info/WHEEL
td0update_darshan-0.1.0.dist-info/licenses/LICENSE
td0update_darshan-0.1.0.dist-info/RECORD
